<?xml version="1.0" encoding="utf-8" ?>
<dwsync>
<file name="index.html" server="trivianightguy.com//public_html/trivianightguy.com/" local="133333598675118857" remote="133332412200000000" Dst="2" />
<file name="jquery-ui.css" server="trivianightguy.com//public_html/trivianightguy.com/" local="133333598676720376" remote="133332412200000000" Dst="2" />
<file name="jquery-ui.min.css" server="trivianightguy.com//public_html/trivianightguy.com/" local="133333598678565001" remote="133332412200000000" Dst="2" />
<file name="jquery-ui.js" server="trivianightguy.com//public_html/trivianightguy.com/" local="133333598680566914" remote="133332412200000000" Dst="2" />
<file name="jquery-ui.min.js" server="trivianightguy.com//public_html/trivianightguy.com/" local="133333598682478751" remote="133332412200000000" Dst="2" />
<file name="jquery-ui.structure.css" server="trivianightguy.com//public_html/trivianightguy.com/" local="133333598682588846" remote="133332412200000000" Dst="2" />
<file name="jquery-ui.structure.min.css" server="trivianightguy.com//public_html/trivianightguy.com/" local="133333598684256184" remote="133332412200000000" Dst="2" />
<file name="jquery-ui.theme.css" server="trivianightguy.com//public_html/trivianightguy.com/" local="133333598684756641" remote="133332412200000000" Dst="2" />
<file name="jquery-ui.theme.min.css" server="trivianightguy.com//public_html/trivianightguy.com/" local="133333598686108640" remote="133332412200000000" Dst="2" />
</dwsync>